{"list":[{"date":"2018-7","arr":{"text":["(1)"],"type":["image"],"month":7,"link":["2018-7-11_(1).JPG"],"year":2018}},{"date":"2018-7","arr":{"text":["(1)syyj","(10)syyj","(11)syyj","(12)syyj","(13)syyj","(2)syyj","(3)syyj","(4)syyj","(5)syyj","(6)syyj","(7)syyj","(8)syyj","(9)syyj"],"type":["image","image","image","image","image","image","image","image","image","image","image","image","image"],"month":7,"link":["2018-7-20_(1)syyj.JPG","2018-7-20_(10)syyj.JPG","2018-7-20_(11)syyj.JPG","2018-7-20_(12)syyj.JPG","2018-7-20_(13)syyj.JPG","2018-7-20_(2)syyj.JPG","2018-7-20_(3)syyj.JPG","2018-7-20_(4)syyj.JPG","2018-7-20_(5)syyj.JPG","2018-7-20_(6)syyj.JPG","2018-7-20_(7)syyj.JPG","2018-7-20_(8)syyj.JPG","2018-7-20_(9)syyj.JPG"],"year":2018}},{"date":"2018-7","arr":{"text":["(1)heb","(10)heb","(11)heb","(12)heb","(2)heb","(3)heb","(4)heb","(5)heb","(6)heb","(7)heb","(8)heb","(9)heb"],"type":["image","image","image","image","image","image","image","image","image","image","image","image"],"month":7,"link":["2018-7-6_(1)heb.JPG","2018-7-6_(10)heb.JPG","2018-7-6_(11)heb.JPG","2018-7-6_(12)heb.JPG","2018-7-6_(2)heb.JPG","2018-7-6_(3)heb.JPG","2018-7-6_(4)heb.JPG","2018-7-6_(5)heb.JPG","2018-7-6_(6)heb.JPG","2018-7-6_(7)heb.JPG","2018-7-6_(8)heb.JPG","2018-7-6_(9)heb.JPG"],"year":2018}},{"date":"2018-7","arr":{"text":["(1)heb","(2)heb","(3)heb","(4)heb","(5)heb"],"type":["image","image","image","image","image"],"month":7,"link":["2018-7-7_(1)heb.JPG","2018-7-7_(2)heb.JPG","2018-7-7_(3)heb.JPG","2018-7-7_(4)heb.JPG","2018-7-7_(5)heb.JPG"],"year":2018}},{"date":"2018-7","arr":{"text":["(1)heb","(10)heb","(11)heb","(12)heb","(13)heb","(14)heb","(15)heb","(16)heb","(17)heb","(18)heb","(2)heb","(3)heb","(4)heb","(5)heb","(6)heb","(7)heb","(8)heb","(9)heb"],"type":["image","image","image","image","image","image","image","image","image","image","image","image","image","image","image","image","image","image"],"month":7,"link":["2018-7-9_(1)heb.JPG","2018-7-9_(10)heb.JPG","2018-7-9_(11)heb.JPG","2018-7-9_(12)heb.JPG","2018-7-9_(13)heb.JPG","2018-7-9_(14)heb.JPG","2018-7-9_(15)heb.JPG","2018-7-9_(16)heb.JPG","2018-7-9_(17)heb.JPG","2018-7-9_(18)heb.JPG","2018-7-9_(2)heb.JPG","2018-7-9_(3)heb.JPG","2018-7-9_(4)heb.JPG","2018-7-9_(5)heb.JPG","2018-7-9_(6)heb.JPG","2018-7-9_(7)heb.JPG","2018-7-9_(8)heb.JPG","2018-7-9_(9)heb.JPG"],"year":2018}},{"date":"2018-6","arr":{"text":["(1)","(10)","(11)","(12)","(13)","(14)","(15)","(2)","(3)","(4)","(5)","(6)","(7)","(8)","(9)"],"type":["image","image","image","image","image","image","image","image","image","image","image","image","image","image","image"],"month":6,"link":["2018-6-20_(1).JPG","2018-6-20_(10).JPG","2018-6-20_(11).JPG","2018-6-20_(12).JPG","2018-6-20_(13).JPG","2018-6-20_(14).JPG","2018-6-20_(15).JPG","2018-6-20_(2).JPG","2018-6-20_(3).JPG","2018-6-20_(4).JPG","2018-6-20_(5).JPG","2018-6-20_(6).JPG","2018-6-20_(7).JPG","2018-6-20_(8).JPG","2018-6-20_(9).JPG"],"year":2018}},{"date":"2018-6","arr":{"text":["(1)","(2)","(3)","(4)"],"type":["image","image","image","image"],"month":6,"link":["2018-6-24_(1).JPG","2018-6-24_(2).JPG","2018-6-24_(3).JPG","2018-6-24_(4).JPG"],"year":2018}},{"date":"2018-6","arr":{"text":["(1)","(2)","(3)","(4)","(5)","(6)","(7)","(8)","(9)"],"type":["image","image","image","image","image","image","image","image","image"],"month":6,"link":["2018-6-25_(1).JPG","2018-6-25_(2).JPG","2018-6-25_(3).JPG","2018-6-25_(4).JPG","2018-6-25_(5).JPG","2018-6-25_(6).JPG","2018-6-25_(7).JPG","2018-6-25_(8).JPG","2018-6-25_(9).JPG"],"year":2018}},{"date":"2018-6","arr":{"text":["(1)","(2)","(3)","(4)"],"type":["image","image","image","image"],"month":6,"link":["2018-6-26_(1).JPG","2018-6-26_(2).JPG","2018-6-26_(3).JPG","2018-6-26_(4).JPG"],"year":2018}},{"date":"2018-6","arr":{"text":["(1)","(2)","(3)","(4)"],"type":["image","image","image","image"],"month":6,"link":["2018-6-7_(1).JPG","2018-6-7_(2).JPG","2018-6-7_(3).JPG","2018-6-7_(4).JPG"],"year":2018}},{"date":"2018-5","arr":{"text":[""],"type":["image"],"month":5,"link":["2018-5-1_.JPG"],"year":2018}},{"date":"2018-5","arr":{"text":["(1)love","(2)love","(3)love","(4)love","(5)love","(6)love"],"type":["image","image","image","image","image","image"],"month":5,"link":["2018-5-20_(1)love.JPG","2018-5-20_(2)love.JPG","2018-5-20_(3)love.JPG","2018-5-20_(4)love.JPG","2018-5-20_(5)love.JPG","2018-5-20_(6)love.JPG"],"year":2018}},{"date":"2018-5","arr":{"text":[""],"type":["image"],"month":5,"link":["2018-5-23_.JPG"],"year":2018}},{"date":"2018-5","arr":{"text":["(1)","(2)","(3)","(4)","(5)","(6)"],"type":["image","image","image","image","image","image"],"month":5,"link":["2018-5-26_(1).JPG","2018-5-26_(2).JPG","2018-5-26_(3).JPG","2018-5-26_(4).JPG","2018-5-26_(5).JPG","2018-5-26_(6).JPG"],"year":2018}},{"date":"2018-5","arr":{"text":["(1)","(2)","(3)"],"type":["image","image","image"],"month":5,"link":["2018-5-28_(1).JPG","2018-5-28_(2).JPG","2018-5-28_(3).JPG"],"year":2018}},{"date":"2018-5","arr":{"text":["(1)","(10)dlyj","(11)dlyj","(12)dlyj","(13)dlyj","(14)dlyj","(15)dlyj","(16)dlyj","(17)dlyj","(2)","(3)dlyj","(4)dlyj","(5)dlyj","(6)dlyj","(7)dlyj","(8)dlyj","(9)dlyj"],"type":["image","image","image","image","image","image","image","image","image","image","image","image","image","image","image","image","image"],"month":5,"link":["2018-5-30_(1).JPG","2018-5-30_(10)dlyj.JPG","2018-5-30_(11)dlyj.JPG","2018-5-30_(12)dlyj.JPG","2018-5-30_(13)dlyj.JPG","2018-5-30_(14)dlyj.JPG","2018-5-30_(15)dlyj.JPG","2018-5-30_(16)dlyj.JPG","2018-5-30_(17)dlyj.JPG","2018-5-30_(2).JPG","2018-5-30_(3)dlyj.JPG","2018-5-30_(4)dlyj.JPG","2018-5-30_(5)dlyj.JPG","2018-5-30_(6)dlyj.JPG","2018-5-30_(7)dlyj.JPG","2018-5-30_(8)dlyj.JPG","2018-5-30_(9)dlyj.JPG"],"year":2018}},{"date":"2018-4","arr":{"text":["(1)dwy","(2)dwy","(3)dwy","(4)dwy","(5)dwy","(6)dwy","(7)dwy","(8)dwy","(9)dwy","hahah"],"type":["image","image","image","image","image","image","image","image","image","image"],"month":4,"link":["2018-4-20_(1)dwy.JPG","2018-4-20_(2)dwy.JPG","2018-4-20_(3)dwy.JPG","2018-4-20_(4)dwy.JPG","2018-4-20_(5)dwy.JPG","2018-4-20_(6)dwy.JPG","2018-4-20_(7)dwy.JPG","2018-4-20_(8)dwy.JPG","2018-4-20_(9)dwy.JPG","2018-4-20_hahah.JPG"],"year":2018}},{"date":"2018-4","arr":{"text":["(1)","(2)","(3)","(4)"],"type":["image","image","image","image"],"month":4,"link":["2018-4-27_(1).JPG","2018-4-27_(2).JPG","2018-4-27_(3).JPG","2018-4-27_(4).JPG"],"year":2018}}]}